[{"complaint_type":"Illegal waste dumping","image":"waste-001.jpg","GPS location":"26.9124,75.7873","severity":"high","status":"open","officer_assigned":"Officer Nisha"},{"complaint_type":"Water leakage","image":"leak-001.jpg","GPS location":"26.9156,75.7892","severity":"medium","status":"assigned","officer_assigned":"Officer Rohit"},{"complaint_type":"Electricity theft","image":"meter-001.jpg","GPS location":"28.6139,77.2090","severity":"high","status":"investigating","officer_assigned":"Officer Meera"},{"complaint_type":"Pollution limit violation","image":"air-001.jpg","GPS location":"28.6276,77.2194","severity":"high","status":"resolved","officer_assigned":"Officer Kavita"}]